{"2019-10-25": {"current_date": "2019-10-25", "previous_date": "2019-10-25", "commitCount": 184, "issueCount": 34, "openIssueCount": 11, "closedIssueCount": 23, "pullRequestCount": 37, "openPullRequestCount": 0, "mergedPullRequestCount": 35, "closedPullRequestCount": 2, "forkCount": 3, "starCount": 6, "watcherCount": 7}, "2019-10-27": {"current_date": "2019-10-27", "previous_date": "2019-10-27", "commitCount": 184, "issueCount": 34, "openIssueCount": 11, "closedIssueCount": 23, "pullRequestCount": 37, "openPullRequestCount": 0, "mergedPullRequestCount": 35, "closedPullRequestCount": 2, "forkCount": 3, "starCount": 6, "watcherCount": 7}, "2019-11-03": {"current_date": "2019-11-03", "previous_date": "2019-10-27", "commitCount": 184, "issueCount": 34, "openIssueCount": 11, "closedIssueCount": 23, "pullRequestCount": 37, "openPullRequestCount": 0, "mergedPullRequestCount": 35, "closedPullRequestCount": 2, "forkCount": 3, "starCount": 6, "watcherCount": 7}}